ml_pylib-0.0.3.dist-info/METADATA
ml_pylib-0.0.3.dist-info/RECORD
ml_pylib-0.0.3.dist-info/WHEEL
ml_pylib-0.0.3.dist-info/top_level.txt
ml_pylib-0.0.3.dist-info/zip-safe
pylib/__init__.py
pylib/util/__init__.py
pylib/util/caffe_.py
pylib/util/cmd.py
pylib/util/dec.py
pylib/util/dtype.py
pylib/util/event.py
pylib/util/feature.py
pylib/util/img.py
pylib/util/io_.py
pylib/util/log.py
pylib/util/mask.py
pylib/util/ml.py
pylib/util/mod.py
pylib/util/neighbour.py
pylib/util/np.py
pylib/util/plt.py
pylib/util/proc.py
pylib/util/progress_bar.py
pylib/util/rand.py
pylib/util/statistic.py
pylib/util/str_.py
pylib/util/t.py
pylib/util/test.py
pylib/util/tf.py
pylib/util/thread_.py
pylib/util/time_.py
pylib/util/url.py
